MANIFEST.in
README.md
README.rst
requirements.txt
setup.py
django_pureftpd_admin.egg-info/PKG-INFO
django_pureftpd_admin.egg-info/SOURCES.txt
django_pureftpd_admin.egg-info/dependency_links.txt
django_pureftpd_admin.egg-info/requires.txt
django_pureftpd_admin.egg-info/top_level.txt
docs/nginx.example.conf
docs/project_settings.py
docs/uwsgi.example.ini
pureftpd_admin/__init__.py
pureftpd_admin/admin.py
pureftpd_admin/forms.py
pureftpd_admin/models.py
pureftpd_admin/settings.py
pureftpd_admin/urls.py
pureftpd_admin/urls.pyc
pureftpd_admin/views.py
pureftpd_admin/localdir/__init__.py
pureftpd_admin/localdir/__init__.pyc
pureftpd_admin/localdir/views.py
pureftpd_admin/localdir/views.pyc
pureftpd_admin/localdir/widgets.py
pureftpd_admin/localdir/widgets.pyc
pureftpd_admin/locale/ru/LC_MESSAGES/django.mo
pureftpd_admin/locale/ru/LC_MESSAGES/django.po
pureftpd_admin/management/__init__.py
pureftpd_admin/management/commands/__init__.py
pureftpd_admin/management/commands/generate_conf.py
pureftpd_admin/static/localdir/css/styles.css
pureftpd_admin/static/localdir/img/folder-red.png
pureftpd_admin/static/localdir/img/folder.png
pureftpd_admin/static/localdir/img/unknown_file.png
pureftpd_admin/static/localdir/js/script.js
pureftpd_admin/templates/localdir/directory_index.html