Metadata-Version: 1.0
Name: django-pureftpd-admin
Version: 0.1.3a
Summary: This is the web base administration interface for pureftpd server
Home-page: https://ivanff@bitbucket.org/ivanff/django-pureftpd-admin
Author: Ivan Fedoseev
Author-email: agestart@gmail.com
License: UNKNOWN
Platform: any
Classifier: Environment :: Web Environment
Classifier: Framework :: Django
Classifier: Intended Audience :: System Administrators
Classifier: Operating System :: OS Independent
Classifier: Programming Language :: Python
Classifier: Programming Language :: Python :: 2.6
Classifier: Programming Language :: Python :: 2.7
Classifier: Topic :: Internet :: WWW/HTTP
Classifier: Topic :: Internet :: WWW/HTTP :: Dynamic Content
